{
  "id": "e30d9f9c-2bff-4b24-be16-f3442c8a7dab",
  "prevId": "00000000-0000-0000-0000-000000000000",
  "version": "7",
  "dialect": "postgresql",
  "tables": {
    "public.order_lines": {
      "name": "order_lines",
      "schema": "",
      "columns": {
        "id": {
          "name": "id",
          "type": "uuid",
          "primaryKey": true,
          "notNull": true,
          "default": "gen_random_uuid()"
        },
        "order_id": {
          "name": "order_id",
          "type": "uuid",
          "primaryKey": false,
          "notNull": true
        },
        "sku": {
          "name": "sku",
          "type": "varchar(64)",
          "primaryKey": false,
          "notNull": true
        },
        "product_name": {
          "name": "product_name",
          "type": "varchar(255)",
          "primaryKey": false,
          "notNull": true
        },
        "quantity": {
          "name": "quantity",
          "type": "integer",
          "primaryKey": false,
          "notNull": true
        },
        "unit_price": {
          "name": "unit_price",
          "type": "numeric(14, 2)",
          "primaryKey": false,
          "notNull": true
        },
        "line_gross": {
          "name": "line_gross",
          "type": "numeric(14, 2)",
          "primaryKey": false,
          "notNull": true
        },
        "line_patronage": {
          "name": "line_patronage",
          "type": "numeric(14, 2)",
          "primaryKey": false,
          "notNull": true,
          "default": "'0'"
        }
      },
      "indexes": {},
      "foreignKeys": {
        "order_lines_order_id_orders_id_fk": {
          "name": "order_lines_order_id_orders_id_fk",
          "tableFrom": "order_lines",
          "tableTo": "orders",
          "columnsFrom": [
            "order_id"
          ],
          "columnsTo": [
            "id"
          ],
          "onDelete": "cascade",
          "onUpdate": "no action"
        }
      },
      "compositePrimaryKeys": {},
      "uniqueConstraints": {},
      "policies": {},
      "checkConstraints": {},
      "isRLSEnabled": false
    },
    "public.orders": {
      "name": "orders",
      "schema": "",
      "columns": {
        "id": {
          "name": "id",
          "type": "uuid",
          "primaryKey": true,
          "notNull": true,
          "default": "gen_random_uuid()"
        },
        "external_id": {
          "name": "external_id",
          "type": "varchar(128)",
          "primaryKey": false,
          "notNull": true
        },
        "guest_email": {
          "name": "guest_email",
          "type": "varchar(255)",
          "primaryKey": false,
          "notNull": false
        },
        "participant_id": {
          "name": "participant_id",
          "type": "uuid",
          "primaryKey": false,
          "notNull": false
        },
        "vendor_code": {
          "name": "vendor_code",
          "type": "varchar(64)",
          "primaryKey": false,
          "notNull": true
        },
        "status": {
          "name": "status",
          "type": "order_status",
          "typeSchema": "public",
          "primaryKey": false,
          "notNull": true,
          "default": "'PENDING_PICKUP'"
        },
        "gross_amount": {
          "name": "gross_amount",
          "type": "numeric(14, 2)",
          "primaryKey": false,
          "notNull": true
        },
        "sales_amount": {
          "name": "sales_amount",
          "type": "numeric(14, 2)",
          "primaryKey": false,
          "notNull": true
        },
        "vendor_payable_amount": {
          "name": "vendor_payable_amount",
          "type": "numeric(14, 2)",
          "primaryKey": false,
          "notNull": true
        },
        "cogs_amount": {
          "name": "cogs_amount",
          "type": "numeric(14, 2)",
          "primaryKey": false,
          "notNull": true,
          "default": "'0'"
        },
        "patronage_amount": {
          "name": "patronage_amount",
          "type": "numeric(14, 2)",
          "primaryKey": false,
          "notNull": true,
          "default": "'0'"
        },
        "currency": {
          "name": "currency",
          "type": "varchar(3)",
          "primaryKey": false,
          "notNull": true,
          "default": "'PHP'"
        },
        "memo": {
          "name": "memo",
          "type": "text",
          "primaryKey": false,
          "notNull": false
        },
        "metadata": {
          "name": "metadata",
          "type": "jsonb",
          "primaryKey": false,
          "notNull": false
        },
        "created_at": {
          "name": "created_at",
          "type": "timestamp with time zone",
          "primaryKey": false,
          "notNull": true,
          "default": "now()"
        },
        "updated_at": {
          "name": "updated_at",
          "type": "timestamp with time zone",
          "primaryKey": false,
          "notNull": true,
          "default": "now()"
        }
      },
      "indexes": {},
      "foreignKeys": {},
      "compositePrimaryKeys": {},
      "uniqueConstraints": {
        "orders_external_id_unique": {
          "name": "orders_external_id_unique",
          "nullsNotDistinct": false,
          "columns": [
            "external_id"
          ]
        }
      },
      "policies": {},
      "checkConstraints": {},
      "isRLSEnabled": false
    },
    "public.patronage_accruals": {
      "name": "patronage_accruals",
      "schema": "",
      "columns": {
        "id": {
          "name": "id",
          "type": "uuid",
          "primaryKey": true,
          "notNull": true,
          "default": "gen_random_uuid()"
        },
        "email_normalized": {
          "name": "email_normalized",
          "type": "varchar(255)",
          "primaryKey": false,
          "notNull": true
        },
        "participant_id": {
          "name": "participant_id",
          "type": "uuid",
          "primaryKey": false,
          "notNull": false
        },
        "order_id": {
          "name": "order_id",
          "type": "uuid",
          "primaryKey": false,
          "notNull": true
        },
        "amount": {
          "name": "amount",
          "type": "numeric(14, 2)",
          "primaryKey": false,
          "notNull": true
        },
        "status": {
          "name": "status",
          "type": "patronage_accrual_status",
          "typeSchema": "public",
          "primaryKey": false,
          "notNull": true,
          "default": "'ACCRUED'"
        },
        "linked_at": {
          "name": "linked_at",
          "type": "timestamp with time zone",
          "primaryKey": false,
          "notNull": false
        },
        "created_at": {
          "name": "created_at",
          "type": "timestamp with time zone",
          "primaryKey": false,
          "notNull": true,
          "default": "now()"
        }
      },
      "indexes": {},
      "foreignKeys": {
        "patronage_accruals_order_id_orders_id_fk": {
          "name": "patronage_accruals_order_id_orders_id_fk",
          "tableFrom": "patronage_accruals",
          "tableTo": "orders",
          "columnsFrom": [
            "order_id"
          ],
          "columnsTo": [
            "id"
          ],
          "onDelete": "cascade",
          "onUpdate": "no action"
        }
      },
      "compositePrimaryKeys": {},
      "uniqueConstraints": {},
      "policies": {},
      "checkConstraints": {},
      "isRLSEnabled": false
    },
    "public.products": {
      "name": "products",
      "schema": "",
      "columns": {
        "id": {
          "name": "id",
          "type": "uuid",
          "primaryKey": true,
          "notNull": true,
          "default": "gen_random_uuid()"
        },
        "vendor_id": {
          "name": "vendor_id",
          "type": "uuid",
          "primaryKey": false,
          "notNull": true
        },
        "sku": {
          "name": "sku",
          "type": "varchar(64)",
          "primaryKey": false,
          "notNull": true
        },
        "name": {
          "name": "name",
          "type": "varchar(255)",
          "primaryKey": false,
          "notNull": true
        },
        "category": {
          "name": "category",
          "type": "varchar(128)",
          "primaryKey": false,
          "notNull": true,
          "default": "'General'"
        },
        "unit_price": {
          "name": "unit_price",
          "type": "numeric(14, 2)",
          "primaryKey": false,
          "notNull": true
        },
        "sales_per_unit": {
          "name": "sales_per_unit",
          "type": "numeric(14, 2)",
          "primaryKey": false,
          "notNull": true
        },
        "vendor_payable_per_unit": {
          "name": "vendor_payable_per_unit",
          "type": "numeric(14, 2)",
          "primaryKey": false,
          "notNull": true
        },
        "cogs_per_unit": {
          "name": "cogs_per_unit",
          "type": "numeric(14, 2)",
          "primaryKey": false,
          "notNull": true,
          "default": "'0'"
        },
        "patronage_per_unit": {
          "name": "patronage_per_unit",
          "type": "numeric(14, 2)",
          "primaryKey": false,
          "notNull": true,
          "default": "'0'"
        },
        "currency": {
          "name": "currency",
          "type": "varchar(3)",
          "primaryKey": false,
          "notNull": true,
          "default": "'PHP'"
        },
        "is_active": {
          "name": "is_active",
          "type": "boolean",
          "primaryKey": false,
          "notNull": true,
          "default": true
        },
        "created_at": {
          "name": "created_at",
          "type": "timestamp with time zone",
          "primaryKey": false,
          "notNull": true,
          "default": "now()"
        },
        "updated_at": {
          "name": "updated_at",
          "type": "timestamp with time zone",
          "primaryKey": false,
          "notNull": true,
          "default": "now()"
        }
      },
      "indexes": {
        "products_vendor_sku_idx": {
          "name": "products_vendor_sku_idx",
          "columns": [
            {
              "expression": "vendor_id",
              "isExpression": false,
              "asc": true,
              "nulls": "last"
            },
            {
              "expression": "sku",
              "isExpression": false,
              "asc": true,
              "nulls": "last"
            }
          ],
          "isUnique": true,
          "concurrently": false,
          "method": "btree",
          "with": {}
        }
      },
      "foreignKeys": {
        "products_vendor_id_vendors_id_fk": {
          "name": "products_vendor_id_vendors_id_fk",
          "tableFrom": "products",
          "tableTo": "vendors",
          "columnsFrom": [
            "vendor_id"
          ],
          "columnsTo": [
            "id"
          ],
          "onDelete": "restrict",
          "onUpdate": "no action"
        }
      },
      "compositePrimaryKeys": {},
      "uniqueConstraints": {},
      "policies": {},
      "checkConstraints": {},
      "isRLSEnabled": false
    },
    "public.vendors": {
      "name": "vendors",
      "schema": "",
      "columns": {
        "id": {
          "name": "id",
          "type": "uuid",
          "primaryKey": true,
          "notNull": true,
          "default": "gen_random_uuid()"
        },
        "code": {
          "name": "code",
          "type": "varchar(64)",
          "primaryKey": false,
          "notNull": true
        },
        "name": {
          "name": "name",
          "type": "varchar(255)",
          "primaryKey": false,
          "notNull": true
        },
        "email": {
          "name": "email",
          "type": "varchar(255)",
          "primaryKey": false,
          "notNull": false
        },
        "is_active": {
          "name": "is_active",
          "type": "boolean",
          "primaryKey": false,
          "notNull": true,
          "default": true
        },
        "created_at": {
          "name": "created_at",
          "type": "timestamp with time zone",
          "primaryKey": false,
          "notNull": true,
          "default": "now()"
        },
        "updated_at": {
          "name": "updated_at",
          "type": "timestamp with time zone",
          "primaryKey": false,
          "notNull": true,
          "default": "now()"
        }
      },
      "indexes": {},
      "foreignKeys": {},
      "compositePrimaryKeys": {},
      "uniqueConstraints": {
        "vendors_code_unique": {
          "name": "vendors_code_unique",
          "nullsNotDistinct": false,
          "columns": [
            "code"
          ]
        }
      },
      "policies": {},
      "checkConstraints": {},
      "isRLSEnabled": false
    }
  },
  "enums": {
    "public.order_status": {
      "name": "order_status",
      "schema": "public",
      "values": [
        "PENDING_PICKUP",
        "PAID",
        "POSTED_TO_LEDGER",
        "FAILED",
        "CANCELLED"
      ]
    },
    "public.patronage_accrual_status": {
      "name": "patronage_accrual_status",
      "schema": "public",
      "values": [
        "ACCRUED",
        "MERGED",
        "PAID_OUT"
      ]
    }
  },
  "schemas": {},
  "sequences": {},
  "roles": {},
  "policies": {},
  "views": {},
  "_meta": {
    "columns": {},
    "schemas": {},
    "tables": {}
  }
}